{
  "SalesJournalId": "91000002",
  "ProFormaDocNo": "91000002",
  "IssueDocNo": "",
  "DeliveryDocNo": "1",
  "InvoiceDocNo": "1",
  "SendToWarehouse": 0,
  "WarehouseId": 1,
  "SalesFiscalYearId": 6,
  "DocNo": "2",
  "DocDate": "14000303",
  "IsCancel": "0",
  "ContractNo": "91000002",
  "CustomerId": "91000002",
  "SalesTypeId": 1,
  "ReceiveTypeId": 1,
  "DiscountTypeId": null,
  "DailyCurrencyRate": "0",
  "CurrencyId": "RLS",
  "CurrencyRateDate": "14000303",
  "UserId": "91000002",
  "BuyerId": "91000000",
  "TotalDocAmount": "10000",
  "NumberOfNextStepDoc": null,
  "TotalDocAmountEquivalentRial": null,
  "TotalAmountAfterDiscountDeduct": null,
  "TotalDiscountAmountEquivalentRial": "0",
  "VoucherRunNo": "بازاریابان ایرانیان زمین",
  "TotalTollAmountEquivalentRial": null,
  "TotalPayableAmount": null,
  "ReceiptDate": null,
  "HasDiscount": null,
  "ReceiptPeriod": null,
  "SalesConfirmLevelId": null,
  "BranchId": null,
  "TotalPreReceiveAmount": "",
  "IsRemainedDoc": "",
  "CustomerGroupId": "",
  "BuyerGroupId": "1",
  "BuyerCenterId": null,
  "CustomerCenterId": "",
  "BeforeYearTrnsfer ": null,
  "NextYearTransfer ": null,
  "EndSalesCycle": null,
  "ProFormaId": "",
  "PreviousStepDocId": "",
  "QuotaGroup": "",
  "SalesDocProduceTypeId": "",
  "ParentIssueDocId": "",
  "ParentDeliveryDocId": "",
  "ProFormaDocDate": "",
  "ParentDocDate": "",
  "IssueDocDate": "",
  "DeliveryDocDate": "",
  "InvoiceDocDate": "",
  "ParentDocNo": "",
  "ParentFactorId": "",
  "TotalCreditDiscountAmount": "",
  "MultimediaDoc": "",
  "MultiMediaDocX": "",
  "SendSms": "",
  "CustomerRequestId": "",
  "ContractNo2": "",
  "SalesJournalItems": [
    {
      "ItemDataId": "0350157",
      "SalesTypeId": 2,
      "ReceiveTypeId": 1,
      "WarehouseId": 1,
      "DiscountTypeId": null,
      "TotalQty": 10,
      "PartialQty": 0,
      "PartialQtyUnitId": 1,
      "TotalQtyUnitId": 1,
      "UnitAmount": 100000,
      "UnitWeightId": 1,
      "State": "4"
    },
    {
      "ItemDataId": "0270315",
      "SalesTypeId": 2,
      "ReceiveTypeId": 1,
      "WarehouseId": 1,
      "DiscountTypeId": null,
      "TotalQty": 10,
      "PartialQty": 0,
      "PartialQtyUnitId": 1,
      "TotalQtyUnitId": 1,
      "UnitAmount": 100000,
      "UnitWeightId": 1,
      "State": "4"
    }
  ]
}
